iqkm/__init__.py
iqkm/__main__.py
iqkm/baseops.py
iqkm/calculate_km_abd.py
iqkm/calculate_km_proximity.py
iqkm/give_pathways_weight.py
iqkm/parse_ko_assignment.py
iqkm/run_hmmsearch.py
iqkm/run_prodigal.py
iqkm/run_remapping.py
iqkm/version.py
iqkm/workflow_identification.py
iqkm/workflow_iqkm.py
iqkm-1.0.dist-info/LICENSE
iqkm-1.0.dist-info/METADATA
iqkm-1.0.dist-info/WHEEL
iqkm-1.0.dist-info/entry_points.txt
iqkm-1.0.dist-info/top_level.txt
iqkm-1.0.dist-info/RECORD
