Metadata-Version: 2.1
Name: iqkm
Version: 1.0
Summary: Identification and quantification of KEGG Modules in metagenomes/genomes
Home-page: https://github.com/Finn-Lab/iqKM/
Author: Jingdi Li
Author-email: lijingdioo@outlook.com
License: GPLv3
Platform: UNKNOWN
Classifier: Programming Language :: Python :: 3.8
Classifier: License :: OSI Approved :: GNU General Public License v3 (GPLv3)
Classifier: Operating System :: Unix
Requires-Python: >=3.6
Requires-Dist: networkx
Requires-Dist: pysam
Requires-Dist: markdown
Requires-Dist: pytest
Requires-Dist: pylint
